vacuum_map_parser_ijai/RobotMap.proto
vacuum_map_parser_ijai/RobotMap_pb2.py
vacuum_map_parser_ijai/RobotMap_pb2.pyi
vacuum_map_parser_ijai/__init__.py
vacuum_map_parser_ijai/aes_decryptor.py
vacuum_map_parser_ijai/beautify_min.py
vacuum_map_parser_ijai/ijai_coordinate_transforms.py
vacuum_map_parser_ijai/image_parser.py
vacuum_map_parser_ijai/map_data_parser.py
vacuum_map_parser_ijai/py.typed
vacuum_map_parser_ijai/status_mapping.py
vacuum_map_parser_ijai-0.1.0.dist-info/LICENSE
vacuum_map_parser_ijai-0.1.0.dist-info/METADATA
vacuum_map_parser_ijai-0.1.0.dist-info/WHEEL
vacuum_map_parser_ijai-0.1.0.dist-info/RECORD
