Metadata-Version: 2.1
Name: vacuum-map-parser-ijai
Version: 0.1.0
Summary: Functionalities for Ijai vacuum map parsing
License: Apache-2.0
Author: maksp86
Author-email: maksp@gsqd.ru
Requires-Python: >=3.11,<4.0
Classifier: Development Status :: 4 - Beta
Classifier: Environment :: Console
Classifier: Intended Audience :: Developers
Classifier: License :: OSI Approved :: Apache Software License
Classifier: Programming Language :: Python :: 3
Classifier: Programming Language :: Python :: 3.11
Classifier: Topic :: Home Automation
Requires-Dist: Pillow
Requires-Dist: pycryptodome
Requires-Dist: vacuum-map-parser-base (>=0.1.5)
Project-URL: Bug Tracker, https://github.com/maksp86/Python-package-vacuum-map-parser-ijai/issues
Project-URL: Changelog, https://github.com/maksp86/Python-package-vacuum-map-parser-ijai/releases
Project-URL: Homepage, https://github.com/maksp86/Python-package-vacuum-map-parser-ijai
Project-URL: Repository, https://github.com/maksp86/Python-package-vacuum-map-parser-ijai
